odoo/addons/partner_identification_import/README.rst
odoo/addons/partner_identification_import/__init__.py
odoo/addons/partner_identification_import/__manifest__.py
odoo/addons/partner_identification_import/i18n/partner_identification_import.pot
odoo/addons/partner_identification_import/models/__init__.py
odoo/addons/partner_identification_import/models/business_document_import.py
odoo/addons/partner_identification_import/readme/CONTRIBUTORS.rst
odoo/addons/partner_identification_import/readme/DESCRIPTION.rst
odoo/addons/partner_identification_import/static/description/icon.png
odoo/addons/partner_identification_import/static/description/index.html
odoo/addons/partner_identification_import/tests/__init__.py
odoo/addons/partner_identification_import/tests/test_business_document_import.py
odoo13_addon_partner_identification_import-13.0.2.0.1.dist-info/METADATA
odoo13_addon_partner_identification_import-13.0.2.0.1.dist-info/WHEEL
odoo13_addon_partner_identification_import-13.0.2.0.1.dist-info/top_level.txt
odoo13_addon_partner_identification_import-13.0.2.0.1.dist-info/RECORD
