Metadata-Version: 2.1
Name: odoo13-addon-partner-identification-import
Version: 13.0.2.0.1
Summary: Provides partner matching on extra ID
Home-page: https://github.com/OCA/edi
Author: BCIM, Odoo Community Association (OCA)
Author-email: support@odoo-community.org
License: AGPL-3
Platform: UNKNOWN
Classifier: Programming Language :: Python
Classifier: Framework :: Odoo
Classifier: Framework :: Odoo :: 13.0
Classifier: License :: OSI Approved :: GNU Affero General Public License v3
Requires-Python: >=3.5
Requires-Dist: odoo13-addon-base-business-document-import
Requires-Dist: odoo13-addon-partner-identification
Requires-Dist: odoo (<13.1dev,>=13.0a)
